termchatter/__init__.py
termchatter/credits.py
termchatter/paths.py
termchatter/pusher_checker.py
termchatter/receive_message.py
termchatter/send_message.py
termchatter/setup.py
termchatter/termchatter.py
termchatter-0.1.6.dist-info/METADATA
termchatter-0.1.6.dist-info/WHEEL
termchatter-0.1.6.dist-info/entry_points.txt
termchatter-0.1.6.dist-info/RECORD
