Metadata-Version: 2.1
Name: termchatter
Version: 0.1.6
Summary: A simple terminal-based chatting app using Pusher
Author: GrimmTMM
Author-email: themagnetboy1207@gmail.com
Requires-Python: >=3.11,<4.0
Classifier: Programming Language :: Python :: 3
Classifier: Programming Language :: Python :: 3.11
Classifier: Programming Language :: Python :: 3.12
Requires-Dist: pusher (>=3.3.2,<4.0.0)
Requires-Dist: pysher (>=1.0.8,<2.0.0)
